{
    "columns": {
        "Age": {"sdtype": "numerical"},
        "Gender": {"sdtype": "categorical"},
        "Air Pollution": {"sdtype": "categorical"},
        "Alcohol Usage": {"sdtype": "categorical"},
        "Dust Allergy": {"sdtype": "categorical"},
        "Occupational Hazards": {"sdtype": "categorical"},
        "Genetic Risk": {"sdtype": "categorical"},
        "Chronic Lung Disease": {"sdtype": "categorical"},
        "Balanced Diet": {"sdtype": "categorical"},
        "Obesity": {"sdtype": "categorical"},
        "Smoking": {"sdtype": "categorical"},
        "Passive Smoker": {"sdtype": "categorical"},
        "Chest Pain": {"sdtype": "categorical"},
        "Coughing of Blood": {"sdtype": "categorical"},
        "Fatigue": {"sdtype": "categorical"},
        "Weight Loss": {"sdtype": "categorical"},
        "Shortness of Breath": {"sdtype": "categorical"},
        "Wheezing": {"sdtype": "categorical"},
        "Swallowing Difficulty": {"sdtype": "categorical"},
        "Clubbing of Finger Nails": {"sdtype": "categorical"},
        "Frequent Cold": {"sdtype": "categorical"},
        "Dry Cough": {"sdtype": "categorical"},
        "Snoring": {"sdtype": "categorical"},
        "Level": {"sdtype": "categorical"}
    },
    "METADATA_SPEC_VERSION": "SINGLE_TABLE_V1"
}